featureforest/__init__.py
featureforest/_feature_extractor_widget.py
featureforest/_segmentation_widget.py
featureforest/napari.yaml
featureforest/exports/__init__.py
featureforest/exports/base.py
featureforest/models/__init__.py
featureforest/models/base.py
featureforest/models/Cellpose/__init__.py
featureforest/models/Cellpose/adapter.py
featureforest/models/Cellpose/cellpose_downsample.py
featureforest/models/Cellpose/cyto3_downsample.pth
featureforest/models/Cellpose/model.py
featureforest/models/DinoV2/__init__.py
featureforest/models/DinoV2/adapter.py
featureforest/models/DinoV2/model.py
featureforest/models/MobileSAM/__init__.py
featureforest/models/MobileSAM/adapter.py
featureforest/models/MobileSAM/model.py
featureforest/models/MobileSAM/tiny_vit_sam.py
featureforest/models/SAM/__init__.py
featureforest/models/SAM/adapter.py
featureforest/models/SAM/model.py
featureforest/models/SAM2/__init__.py
featureforest/models/SAM2/adapter.py
featureforest/models/SAM2/model.py
featureforest/postprocess/__init__.py
featureforest/postprocess/mean_curvature.py
featureforest/postprocess/postprocess.py
featureforest/postprocess/postprocess_with_sam.py
featureforest/utils/__init__.py
featureforest/utils/colormaps.py
featureforest/utils/config.py
featureforest/utils/data.py
featureforest/utils/dataset.py
featureforest/utils/downloader.py
featureforest/utils/extract.py
featureforest/utils/pipeline_prediction.py
featureforest/utils/usage_stats.py
featureforest/widgets/__init__.py
featureforest/widgets/scroll_wrapper.py
featureforest/widgets/usage_stats.py
featureforest/widgets/utils.py
featureforest-0.1.2.dist-info/METADATA
featureforest-0.1.2.dist-info/WHEEL
featureforest-0.1.2.dist-info/entry_points.txt
featureforest-0.1.2.dist-info/licenses/LICENSE
featureforest-0.1.2.dist-info/RECORD
