Metadata-Version: 2.4
Name: featureforest
Version: 0.1.2
Summary: A napari plugin for segmentation using vision transformer features
Project-URL: homepage, https://featureforest.github.io/
Project-URL: repository, https://github.com/juglab/featureforest
Author-email: Mehdi Seifi <mehdi.seifi@fht.org>, Vera Galinova <vera.galinova@fht.org>
License: BSD-3-Clause
License-File: LICENSE
Classifier: Development Status :: 3 - Alpha
Classifier: Framework :: napari
Classifier: License :: OSI Approved :: BSD License
Classifier: Programming Language :: Python :: 3
Classifier: Programming Language :: Python :: 3.10
Classifier: Programming Language :: Python :: 3.11
Classifier: Programming Language :: Python :: 3.12
Classifier: Topic :: Scientific/Engineering :: Image Processing
Requires-Python: >=3.10
Requires-Dist: h5py
Requires-Dist: iopath>=0.1.10
Requires-Dist: magicgui
Requires-Dist: matplotlib
Requires-Dist: napari[all]
Requires-Dist: numpy<2.2
Requires-Dist: opencv-python
Requires-Dist: pims
Requires-Dist: pooch
Requires-Dist: pynrrd
Requires-Dist: qtpy
Requires-Dist: scikit-image
Requires-Dist: scikit-learn
Requires-Dist: scipy
Requires-Dist: tifffile
Requires-Dist: timm
Requires-Dist: torch>=2.5.1
Requires-Dist: torchvision>=0.20.1
Requires-Dist: tqdm>=4.66.1
Provides-Extra: dev
Requires-Dist: mkdocs-material; extra == 'dev'
Requires-Dist: pre-commit; extra == 'dev'
Requires-Dist: pytest; extra == 'dev'
Requires-Dist: pytest-cov; extra == 'dev'
Requires-Dist: sybil; extra == 'dev'
Requires-Dist: tox; extra == 'dev'
Requires-Dist: tox-gh-actions; extra == 'dev'
